Workbook

Sheet Hypotheses
A1: Business Plan - L'Etudiant x Alberthon | Hypotheses & Parametres
A2: Blue = inputs modifiables | Periode : 2026-2028 | Montants en EUR
A4: PRODUIT 1 - Barometre des Intentions d'Orientation (SaaS annuel)
A5: Hypothese | B5: Description | C5: An 1 (2026) | D5: An 2 (2027) | E5: An 3 (2028) | F5: Unite | G5: Source / Note
B6: Marche total etablissements FR | C6: 3500 | D6: 3500 | E6: 3500 | F6: etabl. | G6: DEPP 2024 - nb etablissements post-bac actifs
B7: Part adressable via reseau L'Etudiant | C7: 0.15 | D7: 0.25 | E7: 0.4 | F7: % | G7: Acceleration via force commerciale
B8: Taux conversion prospects -> clients | C8: 0.05 | D8: 0.08 | E8: 0.1 | F8: % | G8: Benchmark SaaS EdTech B2B : 5-10% | H8: INCERTAIN
B9: Nb clients Barometre (calcule) | C9: =ROUND(C6*C7*C8,0) -> 26 | D9: =ROUND(C6*D7*D8,0) -> 70 | E9: =ROUND(C6*E7*E8,0) -> 140 | F9: clients | G9: calcule : TAM x SAM% x Taux conversion
B10: Part tier Starter | C10: 0.6 | D10: 0.55 | E10: 0.5 | F10: % | G10: BTS, IUT locaux
B11: Part tier Growth | C11: 0.3 | D11: 0.32 | E11: 0.33 | F11: % | G11: Ecoles mid-market
B12: Part tier Premium | C12: 0.1 | D12: 0.13 | E12: 0.17 | F12: % | G12: Grandes ecoles, universites
B13: Prix annuel Starter | C13: 6000 | D13: 6300 | E13: 6600 | F13: EUR | G13: +5%/an
B14: Prix annuel Growth | C14: 14000 | D14: 14700 | E14: 15400 | F14: EUR | G14: +5%/an
B15: Prix annuel Premium | C15: 28000 | D15: 29400 | E15: 30870 | F15: EUR | G15: +5%/an
B16: Taux de churn annuel P1 | C16: 0.15 | D16: 0.12 | E16: 0.1 | F16: % | G16: Conservateur - amelioration produit | H16: INCERTAIN
A18: PRODUIT 2 - Leads Qualifies Intent-Based (CPL)
A19: Hypothese | B19: Description | C19: An 1 (2026) | D19: An 2 (2027) | E19: An 3 (2028) | F19: Unite | G19: Source / Note
B20: Nb etablissements clients leads | C20: 20 | D20: 55 | E20: 130 | F20: clients | G20: Hypothese commerciale terrain | H20: INCERTAIN
B21: Spend moyen leads/client/an | C21: 15000 | D21: 20000 | E21: 26000 | F21: EUR | G21: Benchmark CPL x volume moyen | H21: INCERTAIN
B22: Part leads A dans mix livre | C22: 0.25 | D22: 0.3 | E22: 0.35 | F22: % | G22: Croit avec amelioration scoring
B23: Part leads B | C23: 0.45 | D23: 0.45 | E23: 0.42 | F23: %
B24: Part leads C | C24: 0.3 | D24: 0.25 | E24: 0.23 | F24: %
B25: Prix moyen lead A | C25: 32 | D25: 34 | E25: 36 | F25: EUR | G25: Premium intention forte
B26: Prix moyen lead B | C26: 11 | D26: 12 | E26: 13 | F26: EUR
B27: Prix moyen lead C | C27: 3 | D27: 3 | E27: 3 | F27: EUR
B28: Churn clients leads | C28: 0.2 | D28: 0.15 | E28: 0.12 | F28: % | G28: Plus volatile que SaaS
A30: COUTS OPERATIONNELS
A31: Hypothese | B31: Description | C31: An 1 (2026) | D31: An 2 (2027) | E31: An 3 (2028) | F31: Unite | G31: Source / Note
B32: Data Engineers (ETP) | C32: 3 | D32: 4 | E32: 5 | F32: ETP | G32: 80k EUR/ETP charge
B33: Cout ETP data (charge) | C33: 80000 | D33: 83200 | E33: 86528 | F33: EUR | G33: +4%/an masse salariale
B34: Sales reps BtoB (ETP) | C34: 2 | D34: 5 | E34: 9 | F34: ETP | G34: 60k EUR/ETP
B35: Cout ETP sales (charge) | C35: 60000 | D35: 62400 | E35: 64896 | F35: EUR | G35: +4%/an
B36: Infrastructure BigQuery + cloud | C36: 8000 | D36: 20000 | E36: 48000 | F36: EUR | G36: Croit avec volumes
B37: Marketing (% du CA) | C37: 0.12 | D37: 0.1 | E37: 0.08 | F37: % | G37: Decrements avec notoriete
B38: G&A (% du CA) | C38: 0.18 | D38: 0.14 | E38: 0.12 | F38: % | G38: Economies d'echelle

Sheet P&L Projection
A1: Compte de Resultat Previsionnel - 2026 / 2027 / 2028
A2: Black = formules liees aux Hypotheses | Montants en EUR
A4: Ligne P&L | B4: An 1 - 2026 | C4: An 2 - 2027 | D4: An 3 - 2028 | E4: CAGR 2026-28
A5: REVENUS
A6: Revenu Produit 1 - Barometre SaaS | B6: =Hypotheses!C9*(Hypotheses!C10*Hypotheses!C13+Hypotheses!C11*Hypotheses!C14+Hypotheses!C12*Hypotheses!C15) -> 275600 | C6: =Hypotheses!D9*(Hypotheses!D10*Hypotheses!D13+Hypotheses!D11*Hypotheses!D14+Hypotheses!D12*Hypotheses!D15) -> 839370 | D6: =Hypotheses!E9*(Hypotheses!E10*Hypotheses!E13+Hypotheses!E11*Hypotheses!E14+Hypotheses!E12*Hypotheses!E15) -> 1908186 | E6: =IFERROR((D6/B6)^(1/2)-1,0) -> 1.6313023
A7: Revenu Produit 2 - Leads CPL | B7: =Hypotheses!C20*Hypotheses!C21 -> 300000 | C7: =Hypotheses!D20*Hypotheses!D21 -> 1100000 | D7: =Hypotheses!E20*Hypotheses!E21 -> 3380000 | E7: =IFERROR((D7/B7)^(1/2)-1,0) -> 2.3565856
A8: REVENU TOTAL | B8: =B6+B7 -> 575600 | C8: =C6+C7 -> 1939370 | D8: =D6+D7 -> 5288186 | E8: =IFERROR((D8/B8)^(1/2)-1,0) -> 2.0310491
A10: MARGE BRUTE
A11: COGS (infra + data directe) | B11: =Hypotheses!C36+(Hypotheses!C32*Hypotheses!C33*0.4) -> 104000 | C11: =Hypotheses!D36+(Hypotheses!D32*Hypotheses!D33*0.4) -> 153120 | D11: =Hypotheses!E36+(Hypotheses!E32*Hypotheses!E33*0.4) -> 221056 | E11: =IFERROR((D11/B11)^(1/2)-1,0) -> 0.45792265
A12: MARGE BRUTE | B12: =B8-B11 -> 471600 | C12: =C8-C11 -> 1786250 | D12: =D8-D11 -> 5067130 | E12: =IFERROR((D12/B12)^(1/2)-1,0) -> 2.2778881
A13: Marge brute (%) | B13: =IFERROR(B12/B8,0) -> 0.81931897 | C13: =IFERROR(C12/C8,0) -> 0.92104653 | D13: =IFERROR(D12/D8,0) -> 0.95819814
A15: CHARGES OPERATIONNELLES
A16: Equipe Data & Engineering | B16: =Hypotheses!C32*Hypotheses!C33 -> 240000 | C16: =Hypotheses!D32*Hypotheses!D33 -> 332800 | D16: =Hypotheses!E32*Hypotheses!E33 -> 432640 | E16: =IFERROR((D16/B16)^(1/2)-1,0) -> 0.34263423
A17: Equipe Sales & Account Mgmt | B17: =Hypotheses!C34*Hypotheses!C35 -> 120000 | C17: =Hypotheses!D34*Hypotheses!D35 -> 312000 | D17: =Hypotheses!E34*Hypotheses!E35 -> 584064 | E17: =IFERROR((D17/B17)^(1/2)-1,0) -> 1.2061732
A18: Marketing & Acquisition | B18: =B8*Hypotheses!C37 -> 69072 | C18: =C8*Hypotheses!D37 -> 193937 | D18: =D8*Hypotheses!E37 -> 423054.88 | E18: =IFERROR((D18/B18)^(1/2)-1,0) -> 1.4748412
A19: G&A (juridique, admin, IT) | B19: =B8*Hypotheses!C38 -> 103608 | C19: =C8*Hypotheses!D38 -> 271511.8 | D19: =D8*Hypotheses!E38 -> 634582.32 | E19: =IFERROR((D19/B19)^(1/2)-1,0) -> 1.4748412
A20: TOTAL OPEX | B20: =SUM(B16:B19) -> 532680 | C20: =SUM(C16:C19) -> 1110248.8 | D20: =SUM(D16:D19) -> 2074341.2 | E20: =IFERROR((D20/B20)^(1/2)-1,0) -> 0.97336264
A22: RESULTAT
A23: EBITDA | B23: =B12-B20 -> -61080 | C23: =C12-C20 -> 676001.2 | D23: =D12-D20 -> 2992788.8 | E23: =IFERROR((D23/B23)^(1/2)-1,0) -> 0
A24: Marge EBITDA (%) | B24: =IFERROR(B23/B8,0) -> -0.10611536 | C24: =IFERROR(C23/C8,0) -> 0.34856742 | D24: =IFERROR(D23/D8,0) -> 0.56593864

Sheet Sensibilite
A1: Analyse de Sensibilite - 2 Variables les plus incertaines
A2: Variable 1 : Taux de conversion P1 (axe vertical) | Variable 2 : Spend moyen leads P2 (axe horizontal)
A4: REVENU TOTAL AN 1 (2026) - Taux conversion P1 x Spend moyen P2
A5: Conv P1 v / Spend P2 > | B5: 10000 | C5: 12000 | D5: 15000 | E5: 18000 | F5: 20000 | G5: 23000 | H5: 26000
A6: 0.03 | B6: 369600 | C6: 409600 | D6: 469600 | E6: 529600 | F6: 569600 | G6: 629600 | H6: 689600
A7: 0.04 | B7: 422600 | C7: 462600 | D7: 522600 | E7: 582600 | F7: 622600 | G7: 682600 | H7: 742600
A8: 0.05 | B8: 475600 | C8: 515600 | D8: 575600 | E8: 635600 | F8: 675600 | G8: 735600 | H8: 795600
A9: 0.06 | B9: 539200 | C9: 579200 | D9: 639200 | E9: 699200 | F9: 739200 | G9: 799200 | H9: 859200
A10: 0.07 | B10: 592200 | C10: 632200 | D10: 692200 | E10: 752200 | F10: 792200 | G10: 852200 | H10: 912200
A11: 0.08 | B11: 645200 | C11: 685200 | D11: 745200 | E11: 805200 | F11: 845200 | G11: 905200 | H11: 965200
A12: 0.1 | B12: 751200 | C12: 791200 | D12: 851200 | E12: 911200 | F12: 951200 | G12: 1011200 | H12: 1071200
A14: REVENU TOTAL AN 3 (2028) - Taux conversion P1 x Spend moyen P2
A15: Conv P1 v / Spend P2 > | B15: 15000 | C15: 18000 | D15: 21000 | E15: 26000 | F15: 30000 | G15: 35000 | H15: 40000
A16: 0.06 | B16: 3094911.6 | C16: 3484911.6 | D16: 3874911.6 | E16: 4524911.6 | F16: 5044911.6 | G16: 5694911.6 | H16: 6344911.6
A17: 0.07 | B17: 3285730.2 | C17: 3675730.2 | D17: 4065730.2 | E17: 4715730.2 | F17: 5235730.2 | G17: 5885730.2 | H17: 6535730.2
A18: 0.08 | B18: 3476548.8 | C18: 3866548.8 | D18: 4256548.8 | E18: 4906548.8 | F18: 5426548.8 | G18: 6076548.8 | H18: 6726548.8
A19: 0.1 | B19: 3858186 | C19: 4248186 | D19: 4638186 | E19: 5288186 | F19: 5808186 | G19: 6458186 | H19: 7108186
A20: 0.12 | B20: 4239823.2 | C20: 4629823.2 | D20: 5019823.2 | E20: 5669823.2 | F20: 6189823.2 | G20: 6839823.2 | H20: 7489823.2
A21: 0.14 | B21: 4621460.4 | C21: 5011460.4 | D21: 5401460.4 | E21: 6051460.4 | F21: 6571460.4 | G21: 7221460.4 | H21: 7871460.4
A22: 0.16 | B22: 5003097.6 | C22: 5393097.6 | D22: 5783097.6 | E22: 6433097.6 | F22: 6953097.6 | G22: 7603097.6 | H22: 8253097.6
A23: LECTURE : La variable la plus sensible est le spend moyen Produit 2 (leads). Une variation +30% (15k->20k EUR/client) genere +100k EUR de revenu en An 1. Sur P1, passer de 5% a 8% de conversion multiplie le revenu par 1.6x. Priorite commerciale : valider 5 clients Barometre et 5 clients Leads avant Q3 2025. Bleu = cas de base. Vert = favorable. Jaune = neutre. Rouge = defavorable.
