Workbook

Sheet Hypotheses
A1: Business Plan — L'Étudiant × Alberthon | Hypothèses & Paramètres
A2: Bleu = inputs modifiables | Période : 2026-2028 | Montants en EUR
A4: PRODUIT 1 — Baromètre des Intentions d'Orientation (SaaS annuel)
A5: Hypothèse | B5: Description | C5: An 1 (2026) | D5: An 2 (2027) | E5: An 3 (2028) | F5: Unité | G5: Source / Note
A6: Marché total établissements FR | B6: Nb établissements post-bac actifs | C6: 3500 | D6: 3500 | E6: 3500 | F6: établ. | G6: DEPP 2024 — nb établissements post-bac actifs
A7: Part adressable réseau L'Étudiant | B7: Couverture via force commerciale | C7: 0.15 | D7: 0.25 | E7: 0.4 | F7: % | G7: Accélération via force commerciale
A8: Taux conversion prospects → clients | B8: Benchmark SaaS EdTech B2B : 5-10% | C8: 0.05 | D8: 0.08 | E8: 0.1 | F8: % | G8: Benchmark SaaS EdTech B2B : 5-10% | H8: INCERTAIN
A9: Nb clients Baromètre (calculé) | B9: Calculé : TAM × SAM% × Taux conversion | C9: =ROUND(C6*C7*C8,0) -> 26 | D9: =ROUND(D6*D7*D8,0) -> 70 | E9: =ROUND(E6*E7*E8,0) -> 140 | F9: clients | G9: Calculé : TAM × SAM% × Taux conversion
A10: Part tier Starter | B10: BTS, IUT locaux | C10: 0.6 | D10: 0.55 | E10: 0.5 | F10: % | G10: BTS, IUT locaux
A11: Part tier Growth | B11: Écoles mid-market | C11: 0.3 | D11: 0.32 | E11: 0.33 | F11: % | G11: Écoles mid-market
A12: Part tier Premium | B12: Grandes écoles, universités | C12: 0.1 | D12: 0.13 | E12: 0.17 | F12: % | G12: Grandes écoles, universités
A13: Prix annuel Starter | B13: +5%/an | C13: 6000 | D13: 6300 | E13: 6600 | F13: EUR | G13: +5%/an
A14: Prix annuel Growth | B14: +5%/an | C14: 14000 | D14: 14700 | E14: 15400 | F14: EUR | G14: +5%/an
A15: Prix annuel Premium | B15: +5%/an | C15: 28000 | D15: 29400 | E15: 30870 | F15: EUR | G15: +5%/an
A16: Taux de churn annuel P1 | B16: Conservateur — amélioration produit | C16: 0.15 | D16: 0.12 | E16: 0.1 | F16: % | G16: Conservateur — amélioration produit | H16: INCERTAIN
A18: PRODUIT 2 — Leads Qualifiés Intent-Based (CPL)
A19: Hypothèse | B19: Description | C19: An 1 (2026) | D19: An 2 (2027) | E19: An 3 (2028) | F19: Unité | G19: Source / Note
A20: Nb établissements clients leads | B20: Hypothèse commerciale terrain | C20: 20 | D20: 55 | E20: 130 | F20: clients | G20: Hypothèse commerciale terrain | H20: INCERTAIN
A21: Spend moyen leads/client/an | B21: Benchmark CPL × volume moyen | C21: 15000 | D21: 20000 | E21: 26000 | F21: EUR | G21: Benchmark CPL × volume moyen | H21: INCERTAIN
A22: Part leads A dans mix livré | B22: Croît avec amélioration scoring | C22: 0.25 | D22: 0.3 | E22: 0.35 | F22: % | G22: Croît avec amélioration scoring
A23: Part leads B | C23: 0.45 | D23: 0.45 | E23: 0.42 | F23: %
A24: Part leads C | C24: 0.3 | D24: 0.25 | E24: 0.23 | F24: %
A25: Prix moyen lead A | B25: Premium intention forte | C25: 32 | D25: 34 | E25: 36 | F25: EUR | G25: Premium intention forte
A26: Prix moyen lead B | C26: 11 | D26: 12 | E26: 13 | F26: EUR
A27: Prix moyen lead C | C27: 3 | D27: 3 | E27: 3 | F27: EUR
A28: Churn clients leads | B28: Plus volatile que SaaS | C28: 0.2 | D28: 0.15 | E28: 0.12 | F28: % | G28: Plus volatile que SaaS
A30: COÛTS OPÉRATIONNELS
A31: Hypothèse | B31: Description | C31: An 1 (2026) | D31: An 2 (2027) | E31: An 3 (2028) | F31: Unité | G31: Source / Note
A32: Data Engineers (ETP) | B32: Build pipeline, scoring, dashboard | C32: 3 | D32: 4 | E32: 5 | F32: ETP | G32: 80 k€/ETP chargé
A33: Coût ETP data (chargé) | B33: +4%/an masse salariale | C33: 80000 | D33: 83200 | E33: 86528 | F33: EUR | G33: +4%/an masse salariale
A34: % coût Data alloué COGS | B34: Run pipeline = COGS ; build = OPEX | C34: 0.4 | D34: 0.4 | E34: 0.4 | F34: % | G34: Convention SaaS : 40% run, 60% build
A35: Sales reps B2B (ETP) | B35: 60 k€/ETP | C35: 2 | D35: 5 | E35: 9 | F35: ETP | G35: 60 k€/ETP
A36: Coût ETP sales (chargé) | B36: +4%/an | C36: 60000 | D36: 62400 | E36: 64896 | F36: EUR | G36: +4%/an
A37: Infrastructure BigQuery + cloud | B37: Croît avec volumes | C37: 8000 | D37: 20000 | E37: 48000 | F37: EUR | G37: Croît avec volumes
A38: Marketing (% du CA) | B38: Décroît avec notoriété | C38: 0.12 | D38: 0.1 | E38: 0.08 | F38: % | G38: Décroît avec notoriété
A39: G&A (% du CA) | B39: Économies d'échelle | C39: 0.18 | D39: 0.14 | E39: 0.12 | F39: % | G39: Économies d'échelle

Sheet P&L Projection
A1: Compte de Résultat Prévisionnel — 2026 / 2027 / 2028
A2: Vert = liens vers Hypothèses | Noir = formules dérivées | Montants EUR | Churn appliqué (×(1−churn/2))
A4: Ligne P&L | B4: An 1 — 2026 | C4: An 2 — 2027 | D4: An 3 — 2028 | E4: CAGR 26-28 | F4: Note
A5: REVENUS (nets de churn)
A6: Revenu Produit 1 — Baromètre SaaS | B6: =Hypotheses!C9*(Hypotheses!C10*Hypotheses!C13+Hypotheses!C11*Hypotheses!C14+Hypotheses!C12*Hypotheses!C15)*(1-Hypotheses!C16/2) -> 254930 | C6: =Hypotheses!D9*(Hypotheses!D10*Hypotheses!D13+Hypotheses!D11*Hypotheses!D14+Hypotheses!D12*Hypotheses!D15)*(1-Hypotheses!D16/2) -> 789007.8 | D6: =Hypotheses!E9*(Hypotheses!E10*Hypotheses!E13+Hypotheses!E11*Hypotheses!E14+Hypotheses!E12*Hypotheses!E15)*(1-Hypotheses!E16/2) -> 1812776.7 | E6: =IFERROR((D6/B6)^(1/2)-1,0) -> 1.6666234 | F6: Net de churn (×(1−churn/2))
A7: Revenu Produit 2 — Leads CPL | B7: =Hypotheses!C20*Hypotheses!C21*(1-Hypotheses!C28/2) -> 270000 | C7: =Hypotheses!D20*Hypotheses!D21*(1-Hypotheses!D28/2) -> 1017500 | D7: =Hypotheses!E20*Hypotheses!E21*(1-Hypotheses!E28/2) -> 3177200 | E7: =IFERROR((D7/B7)^(1/2)-1,0) -> 2.4303655 | F7: Net de churn (×(1−churn/2))
A8: REVENU TOTAL | B8: =B6+B7 -> 524930 | C8: =C6+C7 -> 1806507.8 | D8: =D6+D7 -> 4989976.7 | E8: =IFERROR((D8/B8)^(1/2)-1,0) -> 2.0831777
A10: MARGE BRUTE
A11: COGS (infra + 40% Data Eng — RUN) | B11: =Hypotheses!C37+(Hypotheses!C32*Hypotheses!C33*Hypotheses!C34) -> 104000 | C11: =Hypotheses!D37+(Hypotheses!D32*Hypotheses!D33*Hypotheses!D34) -> 153120 | D11: =Hypotheses!E37+(Hypotheses!E32*Hypotheses!E33*Hypotheses!E34) -> 221056 | E11: =IFERROR((D11/B11)^(1/2)-1,0) -> 0.45792265 | F11: 40% Data → COGS (run). Complément 60% → OPEX (build).
A12: MARGE BRUTE | B12: =B8-B11 -> 420930 | C12: =C8-C11 -> 1653387.8 | D12: =D8-D11 -> 4768920.7 | E12: =IFERROR((D12/B12)^(1/2)-1,0) -> 2.3659302
A13: Marge brute (%) | B13: =IFERROR(B12/B8,0) -> 0.80187835 | C13: =IFERROR(C12/C8,0) -> 0.91523978 | D13: =IFERROR(D12/D8,0) -> 0.95569999
A15: CHARGES OPÉRATIONNELLES
A16: Équipe Data & Eng (60% — BUILD) | B16: =Hypotheses!C32*Hypotheses!C33*(1-Hypotheses!C34) -> 144000 | C16: =Hypotheses!D32*Hypotheses!D33*(1-Hypotheses!D34) -> 199680 | D16: =Hypotheses!E32*Hypotheses!E33*(1-Hypotheses!E34) -> 259584 | E16: =IFERROR((D16/B16)^(1/2)-1,0) -> 0.34263423 | F16: 60% build (complément du 40% COGS)
A17: Équipe Sales & Account Mgmt | B17: =Hypotheses!C35*Hypotheses!C36 -> 120000 | C17: =Hypotheses!D35*Hypotheses!D36 -> 312000 | D17: =Hypotheses!E35*Hypotheses!E36 -> 584064 | E17: =IFERROR((D17/B17)^(1/2)-1,0) -> 1.2061732
A18: Marketing & Acquisition | B18: =B8*Hypotheses!C38 -> 62991.6 | C18: =C8*Hypotheses!D38 -> 180650.78 | D18: =D8*Hypotheses!E38 -> 399198.14 | E18: =IFERROR((D18/B18)^(1/2)-1,0) -> 1.5174041
A19: G&A (juridique, admin, IT) | B19: =B8*Hypotheses!C39 -> 94487.4 | C19: =C8*Hypotheses!D39 -> 252911.09 | D19: =D8*Hypotheses!E39 -> 598797.2 | E19: =IFERROR((D19/B19)^(1/2)-1,0) -> 1.5174041
A20: TOTAL OPEX | B20: =SUM(B16:B19) -> 421479 | C20: =SUM(C16:C19) -> 945241.87 | D20: =SUM(D16:D19) -> 1841643.3 | E20: =IFERROR((D20/B20)^(1/2)-1,0) -> 1.0903297
A22: RÉSULTAT
A23: EBITDA | B23: =B12-B20 -> -549 | C23: =C12-C20 -> 708145.93 | D23: =D12-D20 -> 2927277.4 | E23: =IFERROR((D23/B23)^(1/2)-1,0) -> 0
A24: Marge EBITDA (%) | B24: =IFERROR(B23/B8,0) -> -0.0010458537 | C24: =IFERROR(C23/C8,0) -> 0.39199716 | D24: =IFERROR(D23/D8,0) -> 0.58663147

Sheet Sensibilite
A1: Analyse de Sensibilité — Taux conversion P1 (vertical) × Spend moyen leads P2 (horizontal)
A3: TABLEAU 1 — REVENU TOTAL AN 1 (2026)
A4: Conv P1 ↓ / Spend P2 → | B4: 10000 | C4: 12000 | D4: 15000 | E4: 18000 | F4: 20000 | G4: 23000 | H4: 26000
A5: 0.03 | B5: =ROUND(Hypotheses!$C$6*Hypotheses!$C$7*$A5,0)*(Hypotheses!$C$10*Hypotheses!$C$13+Hypotheses!$C$11*Hypotheses!$C$14+Hypotheses!$C$12*Hypotheses!$C$15)*(1-Hypotheses!$C$16/2)+Hypotheses!$C$20*B$4*(1-Hypotheses!$C$28/2) -> 336880 | C5: =ROUND(Hypotheses!$C$6*Hypotheses!$C$7*$A5,0)*(Hypotheses!$C$10*Hypotheses!$C$13+Hypotheses!$C$11*Hypotheses!$C$14+Hypotheses!$C$12*Hypotheses!$C$15)*(1-Hypotheses!$C$16/2)+Hypotheses!$C$20*C$4*(1-Hypotheses!$C$28/2) -> 372880 | D5: =ROUND(Hypotheses!$C$6*Hypotheses!$C$7*$A5,0)*(Hypotheses!$C$10*Hypotheses!$C$13+Hypotheses!$C$11*Hypotheses!$C$14+Hypotheses!$C$12*Hypotheses!$C$15)*(1-Hypotheses!$C$16/2)+Hypotheses!$C$20*D$4*(1-Hypotheses!$C$28/2) -> 426880 | E5: =ROUND(Hypotheses!$C$6*Hypotheses!$C$7*$A5,0)*(Hypotheses!$C$10*Hypotheses!$C$13+Hypotheses!$C$11*Hypotheses!$C$14+Hypotheses!$C$12*Hypotheses!$C$15)*(1-Hypotheses!$C$16/2)+Hypotheses!$C$20*E$4*(1-Hypotheses!$C$28/2) -> 480880 | F5: =ROUND(Hypotheses!$C$6*Hypotheses!$C$7*$A5,0)*(Hypotheses!$C$10*Hypotheses!$C$13+Hypotheses!$C$11*Hypotheses!$C$14+Hypotheses!$C$12*Hypotheses!$C$15)*(1-Hypotheses!$C$16/2)+Hypotheses!$C$20*F$4*(1-Hypotheses!$C$28/2) -> 516880 | G5: =ROUND(Hypotheses!$C$6*Hypotheses!$C$7*$A5,0)*(Hypotheses!$C$10*Hypotheses!$C$13+Hypotheses!$C$11*Hypotheses!$C$14+Hypotheses!$C$12*Hypotheses!$C$15)*(1-Hypotheses!$C$16/2)+Hypotheses!$C$20*G$4*(1-Hypotheses!$C$28/2) -> 570880 | H5: =ROUND(Hypotheses!$C$6*Hypotheses!$C$7*$A5,0)*(Hypotheses!$C$10*Hypotheses!$C$13+Hypotheses!$C$11*Hypotheses!$C$14+Hypotheses!$C$12*Hypotheses!$C$15)*(1-Hypotheses!$C$16/2)+Hypotheses!$C$20*H$4*(1-Hypotheses!$C$28/2) -> 624880
A6: 0.04 | B6: =ROUND(Hypotheses!$C$6*Hypotheses!$C$7*$A6,0)*(Hypotheses!$C$10*Hypotheses!$C$13+Hypotheses!$C$11*Hypotheses!$C$14+Hypotheses!$C$12*Hypotheses!$C$15)*(1-Hypotheses!$C$16/2)+Hypotheses!$C$20*B$4*(1-Hypotheses!$C$28/2) -> 385905 | C6: =ROUND(Hypotheses!$C$6*Hypotheses!$C$7*$A6,0)*(Hypotheses!$C$10*Hypotheses!$C$13+Hypotheses!$C$11*Hypotheses!$C$14+Hypotheses!$C$12*Hypotheses!$C$15)*(1-Hypotheses!$C$16/2)+Hypotheses!$C$20*C$4*(1-Hypotheses!$C$28/2) -> 421905 | D6: =ROUND(Hypotheses!$C$6*Hypotheses!$C$7*$A6,0)*(Hypotheses!$C$10*Hypotheses!$C$13+Hypotheses!$C$11*Hypotheses!$C$14+Hypotheses!$C$12*Hypotheses!$C$15)*(1-Hypotheses!$C$16/2)+Hypotheses!$C$20*D$4*(1-Hypotheses!$C$28/2) -> 475905 | E6: =ROUND(Hypotheses!$C$6*Hypotheses!$C$7*$A6,0)*(Hypotheses!$C$10*Hypotheses!$C$13+Hypotheses!$C$11*Hypotheses!$C$14+Hypotheses!$C$12*Hypotheses!$C$15)*(1-Hypotheses!$C$16/2)+Hypotheses!$C$20*E$4*(1-Hypotheses!$C$28/2) -> 529905 | F6: =ROUND(Hypotheses!$C$6*Hypotheses!$C$7*$A6,0)*(Hypotheses!$C$10*Hypotheses!$C$13+Hypotheses!$C$11*Hypotheses!$C$14+Hypotheses!$C$12*Hypotheses!$C$15)*(1-Hypotheses!$C$16/2)+Hypotheses!$C$20*F$4*(1-Hypotheses!$C$28/2) -> 565905 | G6: =ROUND(Hypotheses!$C$6*Hypotheses!$C$7*$A6,0)*(Hypotheses!$C$10*Hypotheses!$C$13+Hypotheses!$C$11*Hypotheses!$C$14+Hypotheses!$C$12*Hypotheses!$C$15)*(1-Hypotheses!$C$16/2)+Hypotheses!$C$20*G$4*(1-Hypotheses!$C$28/2) -> 619905 | H6: =ROUND(Hypotheses!$C$6*Hypotheses!$C$7*$A6,0)*(Hypotheses!$C$10*Hypotheses!$C$13+Hypotheses!$C$11*Hypotheses!$C$14+Hypotheses!$C$12*Hypotheses!$C$15)*(1-Hypotheses!$C$16/2)+Hypotheses!$C$20*H$4*(1-Hypotheses!$C$28/2) -> 673905
A7: 0.05 | B7: =ROUND(Hypotheses!$C$6*Hypotheses!$C$7*$A7,0)*(Hypotheses!$C$10*Hypotheses!$C$13+Hypotheses!$C$11*Hypotheses!$C$14+Hypotheses!$C$12*Hypotheses!$C$15)*(1-Hypotheses!$C$16/2)+Hypotheses!$C$20*B$4*(1-Hypotheses!$C$28/2) -> 434930 | C7: =ROUND(Hypotheses!$C$6*Hypotheses!$C$7*$A7,0)*(Hypotheses!$C$10*Hypotheses!$C$13+Hypotheses!$C$11*Hypotheses!$C$14+Hypotheses!$C$12*Hypotheses!$C$15)*(1-Hypotheses!$C$16/2)+Hypotheses!$C$20*C$4*(1-Hypotheses!$C$28/2) -> 470930 | D7: =ROUND(Hypotheses!$C$6*Hypotheses!$C$7*$A7,0)*(Hypotheses!$C$10*Hypotheses!$C$13+Hypotheses!$C$11*Hypotheses!$C$14+Hypotheses!$C$12*Hypotheses!$C$15)*(1-Hypotheses!$C$16/2)+Hypotheses!$C$20*D$4*(1-Hypotheses!$C$28/2) -> 524930 | E7: =ROUND(Hypotheses!$C$6*Hypotheses!$C$7*$A7,0)*(Hypotheses!$C$10*Hypotheses!$C$13+Hypotheses!$C$11*Hypotheses!$C$14+Hypotheses!$C$12*Hypotheses!$C$15)*(1-Hypotheses!$C$16/2)+Hypotheses!$C$20*E$4*(1-Hypotheses!$C$28/2) -> 578930 | F7: =ROUND(Hypotheses!$C$6*Hypotheses!$C$7*$A7,0)*(Hypotheses!$C$10*Hypotheses!$C$13+Hypotheses!$C$11*Hypotheses!$C$14+Hypotheses!$C$12*Hypotheses!$C$15)*(1-Hypotheses!$C$16/2)+Hypotheses!$C$20*F$4*(1-Hypotheses!$C$28/2) -> 614930 | G7: =ROUND(Hypotheses!$C$6*Hypotheses!$C$7*$A7,0)*(Hypotheses!$C$10*Hypotheses!$C$13+Hypotheses!$C$11*Hypotheses!$C$14+Hypotheses!$C$12*Hypotheses!$C$15)*(1-Hypotheses!$C$16/2)+Hypotheses!$C$20*G$4*(1-Hypotheses!$C$28/2) -> 668930 | H7: =ROUND(Hypotheses!$C$6*Hypotheses!$C$7*$A7,0)*(Hypotheses!$C$10*Hypotheses!$C$13+Hypotheses!$C$11*Hypotheses!$C$14+Hypotheses!$C$12*Hypotheses!$C$15)*(1-Hypotheses!$C$16/2)+Hypotheses!$C$20*H$4*(1-Hypotheses!$C$28/2) -> 722930
A8: 0.06 | B8: =ROUND(Hypotheses!$C$6*Hypotheses!$C$7*$A8,0)*(Hypotheses!$C$10*Hypotheses!$C$13+Hypotheses!$C$11*Hypotheses!$C$14+Hypotheses!$C$12*Hypotheses!$C$15)*(1-Hypotheses!$C$16/2)+Hypotheses!$C$20*B$4*(1-Hypotheses!$C$28/2) -> 493760 | C8: =ROUND(Hypotheses!$C$6*Hypotheses!$C$7*$A8,0)*(Hypotheses!$C$10*Hypotheses!$C$13+Hypotheses!$C$11*Hypotheses!$C$14+Hypotheses!$C$12*Hypotheses!$C$15)*(1-Hypotheses!$C$16/2)+Hypotheses!$C$20*C$4*(1-Hypotheses!$C$28/2) -> 529760 | D8: =ROUND(Hypotheses!$C$6*Hypotheses!$C$7*$A8,0)*(Hypotheses!$C$10*Hypotheses!$C$13+Hypotheses!$C$11*Hypotheses!$C$14+Hypotheses!$C$12*Hypotheses!$C$15)*(1-Hypotheses!$C$16/2)+Hypotheses!$C$20*D$4*(1-Hypotheses!$C$28/2) -> 583760 | E8: =ROUND(Hypotheses!$C$6*Hypotheses!$C$7*$A8,0)*(Hypotheses!$C$10*Hypotheses!$C$13+Hypotheses!$C$11*Hypotheses!$C$14+Hypotheses!$C$12*Hypotheses!$C$15)*(1-Hypotheses!$C$16/2)+Hypotheses!$C$20*E$4*(1-Hypotheses!$C$28/2) -> 637760 | F8: =ROUND(Hypotheses!$C$6*Hypotheses!$C$7*$A8,0)*(Hypotheses!$C$10*Hypotheses!$C$13+Hypotheses!$C$11*Hypotheses!$C$14+Hypotheses!$C$12*Hypotheses!$C$15)*(1-Hypotheses!$C$16/2)+Hypotheses!$C$20*F$4*(1-Hypotheses!$C$28/2) -> 673760 | G8: =ROUND(Hypotheses!$C$6*Hypotheses!$C$7*$A8,0)*(Hypotheses!$C$10*Hypotheses!$C$13+Hypotheses!$C$11*Hypotheses!$C$14+Hypotheses!$C$12*Hypotheses!$C$15)*(1-Hypotheses!$C$16/2)+Hypotheses!$C$20*G$4*(1-Hypotheses!$C$28/2) -> 727760 | H8: =ROUND(Hypotheses!$C$6*Hypotheses!$C$7*$A8,0)*(Hypotheses!$C$10*Hypotheses!$C$13+Hypotheses!$C$11*Hypotheses!$C$14+Hypotheses!$C$12*Hypotheses!$C$15)*(1-Hypotheses!$C$16/2)+Hypotheses!$C$20*H$4*(1-Hypotheses!$C$28/2) -> 781760
A9: 0.07 | B9: =ROUND(Hypotheses!$C$6*Hypotheses!$C$7*$A9,0)*(Hypotheses!$C$10*Hypotheses!$C$13+Hypotheses!$C$11*Hypotheses!$C$14+Hypotheses!$C$12*Hypotheses!$C$15)*(1-Hypotheses!$C$16/2)+Hypotheses!$C$20*B$4*(1-Hypotheses!$C$28/2) -> 542785 | C9: =ROUND(Hypotheses!$C$6*Hypotheses!$C$7*$A9,0)*(Hypotheses!$C$10*Hypotheses!$C$13+Hypotheses!$C$11*Hypotheses!$C$14+Hypotheses!$C$12*Hypotheses!$C$15)*(1-Hypotheses!$C$16/2)+Hypotheses!$C$20*C$4*(1-Hypotheses!$C$28/2) -> 578785 | D9: =ROUND(Hypotheses!$C$6*Hypotheses!$C$7*$A9,0)*(Hypotheses!$C$10*Hypotheses!$C$13+Hypotheses!$C$11*Hypotheses!$C$14+Hypotheses!$C$12*Hypotheses!$C$15)*(1-Hypotheses!$C$16/2)+Hypotheses!$C$20*D$4*(1-Hypotheses!$C$28/2) -> 632785 | E9: =ROUND(Hypotheses!$C$6*Hypotheses!$C$7*$A9,0)*(Hypotheses!$C$10*Hypotheses!$C$13+Hypotheses!$C$11*Hypotheses!$C$14+Hypotheses!$C$12*Hypotheses!$C$15)*(1-Hypotheses!$C$16/2)+Hypotheses!$C$20*E$4*(1-Hypotheses!$C$28/2) -> 686785 | F9: =ROUND(Hypotheses!$C$6*Hypotheses!$C$7*$A9,0)*(Hypotheses!$C$10*Hypotheses!$C$13+Hypotheses!$C$11*Hypotheses!$C$14+Hypotheses!$C$12*Hypotheses!$C$15)*(1-Hypotheses!$C$16/2)+Hypotheses!$C$20*F$4*(1-Hypotheses!$C$28/2) -> 722785 | G9: =ROUND(Hypotheses!$C$6*Hypotheses!$C$7*$A9,0)*(Hypotheses!$C$10*Hypotheses!$C$13+Hypotheses!$C$11*Hypotheses!$C$14+Hypotheses!$C$12*Hypotheses!$C$15)*(1-Hypotheses!$C$16/2)+Hypotheses!$C$20*G$4*(1-Hypotheses!$C$28/2) -> 776785 | H9: =ROUND(Hypotheses!$C$6*Hypotheses!$C$7*$A9,0)*(Hypotheses!$C$10*Hypotheses!$C$13+Hypotheses!$C$11*Hypotheses!$C$14+Hypotheses!$C$12*Hypotheses!$C$15)*(1-Hypotheses!$C$16/2)+Hypotheses!$C$20*H$4*(1-Hypotheses!$C$28/2) -> 830785
A10: 0.08 | B10: =ROUND(Hypotheses!$C$6*Hypotheses!$C$7*$A10,0)*(Hypotheses!$C$10*Hypotheses!$C$13+Hypotheses!$C$11*Hypotheses!$C$14+Hypotheses!$C$12*Hypotheses!$C$15)*(1-Hypotheses!$C$16/2)+Hypotheses!$C$20*B$4*(1-Hypotheses!$C$28/2) -> 591810 | C10: =ROUND(Hypotheses!$C$6*Hypotheses!$C$7*$A10,0)*(Hypotheses!$C$10*Hypotheses!$C$13+Hypotheses!$C$11*Hypotheses!$C$14+Hypotheses!$C$12*Hypotheses!$C$15)*(1-Hypotheses!$C$16/2)+Hypotheses!$C$20*C$4*(1-Hypotheses!$C$28/2) -> 627810 | D10: =ROUND(Hypotheses!$C$6*Hypotheses!$C$7*$A10,0)*(Hypotheses!$C$10*Hypotheses!$C$13+Hypotheses!$C$11*Hypotheses!$C$14+Hypotheses!$C$12*Hypotheses!$C$15)*(1-Hypotheses!$C$16/2)+Hypotheses!$C$20*D$4*(1-Hypotheses!$C$28/2) -> 681810 | E10: =ROUND(Hypotheses!$C$6*Hypotheses!$C$7*$A10,0)*(Hypotheses!$C$10*Hypotheses!$C$13+Hypotheses!$C$11*Hypotheses!$C$14+Hypotheses!$C$12*Hypotheses!$C$15)*(1-Hypotheses!$C$16/2)+Hypotheses!$C$20*E$4*(1-Hypotheses!$C$28/2) -> 735810 | F10: =ROUND(Hypotheses!$C$6*Hypotheses!$C$7*$A10,0)*(Hypotheses!$C$10*Hypotheses!$C$13+Hypotheses!$C$11*Hypotheses!$C$14+Hypotheses!$C$12*Hypotheses!$C$15)*(1-Hypotheses!$C$16/2)+Hypotheses!$C$20*F$4*(1-Hypotheses!$C$28/2) -> 771810 | G10: =ROUND(Hypotheses!$C$6*Hypotheses!$C$7*$A10,0)*(Hypotheses!$C$10*Hypotheses!$C$13+Hypotheses!$C$11*Hypotheses!$C$14+Hypotheses!$C$12*Hypotheses!$C$15)*(1-Hypotheses!$C$16/2)+Hypotheses!$C$20*G$4*(1-Hypotheses!$C$28/2) -> 825810 | H10: =ROUND(Hypotheses!$C$6*Hypotheses!$C$7*$A10,0)*(Hypotheses!$C$10*Hypotheses!$C$13+Hypotheses!$C$11*Hypotheses!$C$14+Hypotheses!$C$12*Hypotheses!$C$15)*(1-Hypotheses!$C$16/2)+Hypotheses!$C$20*H$4*(1-Hypotheses!$C$28/2) -> 879810
A11: 0.1 | B11: =ROUND(Hypotheses!$C$6*Hypotheses!$C$7*$A11,0)*(Hypotheses!$C$10*Hypotheses!$C$13+Hypotheses!$C$11*Hypotheses!$C$14+Hypotheses!$C$12*Hypotheses!$C$15)*(1-Hypotheses!$C$16/2)+Hypotheses!$C$20*B$4*(1-Hypotheses!$C$28/2) -> 699665 | C11: =ROUND(Hypotheses!$C$6*Hypotheses!$C$7*$A11,0)*(Hypotheses!$C$10*Hypotheses!$C$13+Hypotheses!$C$11*Hypotheses!$C$14+Hypotheses!$C$12*Hypotheses!$C$15)*(1-Hypotheses!$C$16/2)+Hypotheses!$C$20*C$4*(1-Hypotheses!$C$28/2) -> 735665 | D11: =ROUND(Hypotheses!$C$6*Hypotheses!$C$7*$A11,0)*(Hypotheses!$C$10*Hypotheses!$C$13+Hypotheses!$C$11*Hypotheses!$C$14+Hypotheses!$C$12*Hypotheses!$C$15)*(1-Hypotheses!$C$16/2)+Hypotheses!$C$20*D$4*(1-Hypotheses!$C$28/2) -> 789665 | E11: =ROUND(Hypotheses!$C$6*Hypotheses!$C$7*$A11,0)*(Hypotheses!$C$10*Hypotheses!$C$13+Hypotheses!$C$11*Hypotheses!$C$14+Hypotheses!$C$12*Hypotheses!$C$15)*(1-Hypotheses!$C$16/2)+Hypotheses!$C$20*E$4*(1-Hypotheses!$C$28/2) -> 843665 | F11: =ROUND(Hypotheses!$C$6*Hypotheses!$C$7*$A11,0)*(Hypotheses!$C$10*Hypotheses!$C$13+Hypotheses!$C$11*Hypotheses!$C$14+Hypotheses!$C$12*Hypotheses!$C$15)*(1-Hypotheses!$C$16/2)+Hypotheses!$C$20*F$4*(1-Hypotheses!$C$28/2) -> 879665 | G11: =ROUND(Hypotheses!$C$6*Hypotheses!$C$7*$A11,0)*(Hypotheses!$C$10*Hypotheses!$C$13+Hypotheses!$C$11*Hypotheses!$C$14+Hypotheses!$C$12*Hypotheses!$C$15)*(1-Hypotheses!$C$16/2)+Hypotheses!$C$20*G$4*(1-Hypotheses!$C$28/2) -> 933665 | H11: =ROUND(Hypotheses!$C$6*Hypotheses!$C$7*$A11,0)*(Hypotheses!$C$10*Hypotheses!$C$13+Hypotheses!$C$11*Hypotheses!$C$14+Hypotheses!$C$12*Hypotheses!$C$15)*(1-Hypotheses!$C$16/2)+Hypotheses!$C$20*H$4*(1-Hypotheses!$C$28/2) -> 987665
A13: TABLEAU 2 — EBITDA AN 3 (2028) — correction : l'original mesurait le Revenu, cette version mesure l'EBITDA
A14: Conv P1 ↓ / Spend P2 → | B14: 15000 | C14: 18000 | D14: 21000 | E14: 26000 | F14: 30000 | G14: 35000 | H14: 40000
A15: 0.06 | B15: =(ROUND(Hypotheses!$E$6*Hypotheses!$E$7*$A15,0)*(Hypotheses!$E$10*Hypotheses!$E$13+Hypotheses!$E$11*Hypotheses!$E$14+Hypotheses!$E$12*Hypotheses!$E$15)*(1-Hypotheses!$E$16/2)+Hypotheses!$E$20*B$14*(1-Hypotheses!$E$28/2))*(1-(Hypotheses!$E$38+Hypotheses!$E$39))-(Hypotheses!$E$37+Hypotheses!$E$32*Hypotheses!$E$33*Hypotheses!$E$34)-(Hypotheses!$E$32*Hypotheses!$E$33*(1-Hypotheses!$E$34))-(Hypotheses!$E$35*Hypotheses!$E$36) -> 1271828.8 | C15: =(ROUND(Hypotheses!$E$6*Hypotheses!$E$7*$A15,0)*(Hypotheses!$E$10*Hypotheses!$E$13+Hypotheses!$E$11*Hypotheses!$E$14+Hypotheses!$E$12*Hypotheses!$E$15)*(1-Hypotheses!$E$16/2)+Hypotheses!$E$20*C$14*(1-Hypotheses!$E$28/2))*(1-(Hypotheses!$E$38+Hypotheses!$E$39))-(Hypotheses!$E$37+Hypotheses!$E$32*Hypotheses!$E$33*Hypotheses!$E$34)-(Hypotheses!$E$32*Hypotheses!$E$33*(1-Hypotheses!$E$34))-(Hypotheses!$E$35*Hypotheses!$E$36) -> 1565108.8 | D15: =(ROUND(Hypotheses!$E$6*Hypotheses!$E$7*$A15,0)*(Hypotheses!$E$10*Hypotheses!$E$13+Hypotheses!$E$11*Hypotheses!$E$14+Hypotheses!$E$12*Hypotheses!$E$15)*(1-Hypotheses!$E$16/2)+Hypotheses!$E$20*D$14*(1-Hypotheses!$E$28/2))*(1-(Hypotheses!$E$38+Hypotheses!$E$39))-(Hypotheses!$E$37+Hypotheses!$E$32*Hypotheses!$E$33*Hypotheses!$E$34)-(Hypotheses!$E$32*Hypotheses!$E$33*(1-Hypotheses!$E$34))-(Hypotheses!$E$35*Hypotheses!$E$36) -> 1858388.8 | E15: =(ROUND(Hypotheses!$E$6*Hypotheses!$E$7*$A15,0)*(Hypotheses!$E$10*Hypotheses!$E$13+Hypotheses!$E$11*Hypotheses!$E$14+Hypotheses!$E$12*Hypotheses!$E$15)*(1-Hypotheses!$E$16/2)+Hypotheses!$E$20*E$14*(1-Hypotheses!$E$28/2))*(1-(Hypotheses!$E$38+Hypotheses!$E$39))-(Hypotheses!$E$37+Hypotheses!$E$32*Hypotheses!$E$33*Hypotheses!$E$34)-(Hypotheses!$E$32*Hypotheses!$E$33*(1-Hypotheses!$E$34))-(Hypotheses!$E$35*Hypotheses!$E$36) -> 2347188.8 | F15: =(ROUND(Hypotheses!$E$6*Hypotheses!$E$7*$A15,0)*(Hypotheses!$E$10*Hypotheses!$E$13+Hypotheses!$E$11*Hypotheses!$E$14+Hypotheses!$E$12*Hypotheses!$E$15)*(1-Hypotheses!$E$16/2)+Hypotheses!$E$20*F$14*(1-Hypotheses!$E$28/2))*(1-(Hypotheses!$E$38+Hypotheses!$E$39))-(Hypotheses!$E$37+Hypotheses!$E$32*Hypotheses!$E$33*Hypotheses!$E$34)-(Hypotheses!$E$32*Hypotheses!$E$33*(1-Hypotheses!$E$34))-(Hypotheses!$E$35*Hypotheses!$E$36) -> 2738228.8 | G15: =(ROUND(Hypotheses!$E$6*Hypotheses!$E$7*$A15,0)*(Hypotheses!$E$10*Hypotheses!$E$13+Hypotheses!$E$11*Hypotheses!$E$14+Hypotheses!$E$12*Hypotheses!$E$15)*(1-Hypotheses!$E$16/2)+Hypotheses!$E$20*G$14*(1-Hypotheses!$E$28/2))*(1-(Hypotheses!$E$38+Hypotheses!$E$39))-(Hypotheses!$E$37+Hypotheses!$E$32*Hypotheses!$E$33*Hypotheses!$E$34)-(Hypotheses!$E$32*Hypotheses!$E$33*(1-Hypotheses!$E$34))-(Hypotheses!$E$35*Hypotheses!$E$36) -> 3227028.8 | H15: =(ROUND(Hypotheses!$E$6*Hypotheses!$E$7*$A15,0)*(Hypotheses!$E$10*Hypotheses!$E$13+Hypotheses!$E$11*Hypotheses!$E$14+Hypotheses!$E$12*Hypotheses!$E$15)*(1-Hypotheses!$E$16/2)+Hypotheses!$E$20*H$14*(1-Hypotheses!$E$28/2))*(1-(Hypotheses!$E$38+Hypotheses!$E$39))-(Hypotheses!$E$37+Hypotheses!$E$32*Hypotheses!$E$33*Hypotheses!$E$34)-(Hypotheses!$E$32*Hypotheses!$E$33*(1-Hypotheses!$E$34))-(Hypotheses!$E$35*Hypotheses!$E$36) -> 3715828.8
A16: 0.07 | B16: =(ROUND(Hypotheses!$E$6*Hypotheses!$E$7*$A16,0)*(Hypotheses!$E$10*Hypotheses!$E$13+Hypotheses!$E$11*Hypotheses!$E$14+Hypotheses!$E$12*Hypotheses!$E$15)*(1-Hypotheses!$E$16/2)+Hypotheses!$E$20*B$14*(1-Hypotheses!$E$28/2))*(1-(Hypotheses!$E$38+Hypotheses!$E$39))-(Hypotheses!$E$37+Hypotheses!$E$32*Hypotheses!$E$33*Hypotheses!$E$34)-(Hypotheses!$E$32*Hypotheses!$E$33*(1-Hypotheses!$E$34))-(Hypotheses!$E$35*Hypotheses!$E$36) -> 1416851 | C16: =(ROUND(Hypotheses!$E$6*Hypotheses!$E$7*$A16,0)*(Hypotheses!$E$10*Hypotheses!$E$13+Hypotheses!$E$11*Hypotheses!$E$14+Hypotheses!$E$12*Hypotheses!$E$15)*(1-Hypotheses!$E$16/2)+Hypotheses!$E$20*C$14*(1-Hypotheses!$E$28/2))*(1-(Hypotheses!$E$38+Hypotheses!$E$39))-(Hypotheses!$E$37+Hypotheses!$E$32*Hypotheses!$E$33*Hypotheses!$E$34)-(Hypotheses!$E$32*Hypotheses!$E$33*(1-Hypotheses!$E$34))-(Hypotheses!$E$35*Hypotheses!$E$36) -> 1710131 | D16: =(ROUND(Hypotheses!$E$6*Hypotheses!$E$7*$A16,0)*(Hypotheses!$E$10*Hypotheses!$E$13+Hypotheses!$E$11*Hypotheses!$E$14+Hypotheses!$E$12*Hypotheses!$E$15)*(1-Hypotheses!$E$16/2)+Hypotheses!$E$20*D$14*(1-Hypotheses!$E$28/2))*(1-(Hypotheses!$E$38+Hypotheses!$E$39))-(Hypotheses!$E$37+Hypotheses!$E$32*Hypotheses!$E$33*Hypotheses!$E$34)-(Hypotheses!$E$32*Hypotheses!$E$33*(1-Hypotheses!$E$34))-(Hypotheses!$E$35*Hypotheses!$E$36) -> 2003411 | E16: =(ROUND(Hypotheses!$E$6*Hypotheses!$E$7*$A16,0)*(Hypotheses!$E$10*Hypotheses!$E$13+Hypotheses!$E$11*Hypotheses!$E$14+Hypotheses!$E$12*Hypotheses!$E$15)*(1-Hypotheses!$E$16/2)+Hypotheses!$E$20*E$14*(1-Hypotheses!$E$28/2))*(1-(Hypotheses!$E$38+Hypotheses!$E$39))-(Hypotheses!$E$37+Hypotheses!$E$32*Hypotheses!$E$33*Hypotheses!$E$34)-(Hypotheses!$E$32*Hypotheses!$E$33*(1-Hypotheses!$E$34))-(Hypotheses!$E$35*Hypotheses!$E$36) -> 2492211 | F16: =(ROUND(Hypotheses!$E$6*Hypotheses!$E$7*$A16,0)*(Hypotheses!$E$10*Hypotheses!$E$13+Hypotheses!$E$11*Hypotheses!$E$14+Hypotheses!$E$12*Hypotheses!$E$15)*(1-Hypotheses!$E$16/2)+Hypotheses!$E$20*F$14*(1-Hypotheses!$E$28/2))*(1-(Hypotheses!$E$38+Hypotheses!$E$39))-(Hypotheses!$E$37+Hypotheses!$E$32*Hypotheses!$E$33*Hypotheses!$E$34)-(Hypotheses!$E$32*Hypotheses!$E$33*(1-Hypotheses!$E$34))-(Hypotheses!$E$35*Hypotheses!$E$36) -> 2883251 | G16: =(ROUND(Hypotheses!$E$6*Hypotheses!$E$7*$A16,0)*(Hypotheses!$E$10*Hypotheses!$E$13+Hypotheses!$E$11*Hypotheses!$E$14+Hypotheses!$E$12*Hypotheses!$E$15)*(1-Hypotheses!$E$16/2)+Hypotheses!$E$20*G$14*(1-Hypotheses!$E$28/2))*(1-(Hypotheses!$E$38+Hypotheses!$E$39))-(Hypotheses!$E$37+Hypotheses!$E$32*Hypotheses!$E$33*Hypotheses!$E$34)-(Hypotheses!$E$32*Hypotheses!$E$33*(1-Hypotheses!$E$34))-(Hypotheses!$E$35*Hypotheses!$E$36) -> 3372051 | H16: =(ROUND(Hypotheses!$E$6*Hypotheses!$E$7*$A16,0)*(Hypotheses!$E$10*Hypotheses!$E$13+Hypotheses!$E$11*Hypotheses!$E$14+Hypotheses!$E$12*Hypotheses!$E$15)*(1-Hypotheses!$E$16/2)+Hypotheses!$E$20*H$14*(1-Hypotheses!$E$28/2))*(1-(Hypotheses!$E$38+Hypotheses!$E$39))-(Hypotheses!$E$37+Hypotheses!$E$32*Hypotheses!$E$33*Hypotheses!$E$34)-(Hypotheses!$E$32*Hypotheses!$E$33*(1-Hypotheses!$E$34))-(Hypotheses!$E$35*Hypotheses!$E$36) -> 3860851
A17: 0.08 | B17: =(ROUND(Hypotheses!$E$6*Hypotheses!$E$7*$A17,0)*(Hypotheses!$E$10*Hypotheses!$E$13+Hypotheses!$E$11*Hypotheses!$E$14+Hypotheses!$E$12*Hypotheses!$E$15)*(1-Hypotheses!$E$16/2)+Hypotheses!$E$20*B$14*(1-Hypotheses!$E$28/2))*(1-(Hypotheses!$E$38+Hypotheses!$E$39))-(Hypotheses!$E$37+Hypotheses!$E$32*Hypotheses!$E$33*Hypotheses!$E$34)-(Hypotheses!$E$32*Hypotheses!$E$33*(1-Hypotheses!$E$34))-(Hypotheses!$E$35*Hypotheses!$E$36) -> 1561873.1 | C17: =(ROUND(Hypotheses!$E$6*Hypotheses!$E$7*$A17,0)*(Hypotheses!$E$10*Hypotheses!$E$13+Hypotheses!$E$11*Hypotheses!$E$14+Hypotheses!$E$12*Hypotheses!$E$15)*(1-Hypotheses!$E$16/2)+Hypotheses!$E$20*C$14*(1-Hypotheses!$E$28/2))*(1-(Hypotheses!$E$38+Hypotheses!$E$39))-(Hypotheses!$E$37+Hypotheses!$E$32*Hypotheses!$E$33*Hypotheses!$E$34)-(Hypotheses!$E$32*Hypotheses!$E$33*(1-Hypotheses!$E$34))-(Hypotheses!$E$35*Hypotheses!$E$36) -> 1855153.1 | D17: =(ROUND(Hypotheses!$E$6*Hypotheses!$E$7*$A17,0)*(Hypotheses!$E$10*Hypotheses!$E$13+Hypotheses!$E$11*Hypotheses!$E$14+Hypotheses!$E$12*Hypotheses!$E$15)*(1-Hypotheses!$E$16/2)+Hypotheses!$E$20*D$14*(1-Hypotheses!$E$28/2))*(1-(Hypotheses!$E$38+Hypotheses!$E$39))-(Hypotheses!$E$37+Hypotheses!$E$32*Hypotheses!$E$33*Hypotheses!$E$34)-(Hypotheses!$E$32*Hypotheses!$E$33*(1-Hypotheses!$E$34))-(Hypotheses!$E$35*Hypotheses!$E$36) -> 2148433.1 | E17: =(ROUND(Hypotheses!$E$6*Hypotheses!$E$7*$A17,0)*(Hypotheses!$E$10*Hypotheses!$E$13+Hypotheses!$E$11*Hypotheses!$E$14+Hypotheses!$E$12*Hypotheses!$E$15)*(1-Hypotheses!$E$16/2)+Hypotheses!$E$20*E$14*(1-Hypotheses!$E$28/2))*(1-(Hypotheses!$E$38+Hypotheses!$E$39))-(Hypotheses!$E$37+Hypotheses!$E$32*Hypotheses!$E$33*Hypotheses!$E$34)-(Hypotheses!$E$32*Hypotheses!$E$33*(1-Hypotheses!$E$34))-(Hypotheses!$E$35*Hypotheses!$E$36) -> 2637233.1 | F17: =(ROUND(Hypotheses!$E$6*Hypotheses!$E$7*$A17,0)*(Hypotheses!$E$10*Hypotheses!$E$13+Hypotheses!$E$11*Hypotheses!$E$14+Hypotheses!$E$12*Hypotheses!$E$15)*(1-Hypotheses!$E$16/2)+Hypotheses!$E$20*F$14*(1-Hypotheses!$E$28/2))*(1-(Hypotheses!$E$38+Hypotheses!$E$39))-(Hypotheses!$E$37+Hypotheses!$E$32*Hypotheses!$E$33*Hypotheses!$E$34)-(Hypotheses!$E$32*Hypotheses!$E$33*(1-Hypotheses!$E$34))-(Hypotheses!$E$35*Hypotheses!$E$36) -> 3028273.1 | G17: =(ROUND(Hypotheses!$E$6*Hypotheses!$E$7*$A17,0)*(Hypotheses!$E$10*Hypotheses!$E$13+Hypotheses!$E$11*Hypotheses!$E$14+Hypotheses!$E$12*Hypotheses!$E$15)*(1-Hypotheses!$E$16/2)+Hypotheses!$E$20*G$14*(1-Hypotheses!$E$28/2))*(1-(Hypotheses!$E$38+Hypotheses!$E$39))-(Hypotheses!$E$37+Hypotheses!$E$32*Hypotheses!$E$33*Hypotheses!$E$34)-(Hypotheses!$E$32*Hypotheses!$E$33*(1-Hypotheses!$E$34))-(Hypotheses!$E$35*Hypotheses!$E$36) -> 3517073.1 | H17: =(ROUND(Hypotheses!$E$6*Hypotheses!$E$7*$A17,0)*(Hypotheses!$E$10*Hypotheses!$E$13+Hypotheses!$E$11*Hypotheses!$E$14+Hypotheses!$E$12*Hypotheses!$E$15)*(1-Hypotheses!$E$16/2)+Hypotheses!$E$20*H$14*(1-Hypotheses!$E$28/2))*(1-(Hypotheses!$E$38+Hypotheses!$E$39))-(Hypotheses!$E$37+Hypotheses!$E$32*Hypotheses!$E$33*Hypotheses!$E$34)-(Hypotheses!$E$32*Hypotheses!$E$33*(1-Hypotheses!$E$34))-(Hypotheses!$E$35*Hypotheses!$E$36) -> 4005873.1
A18: 0.1 | B18: =(ROUND(Hypotheses!$E$6*Hypotheses!$E$7*$A18,0)*(Hypotheses!$E$10*Hypotheses!$E$13+Hypotheses!$E$11*Hypotheses!$E$14+Hypotheses!$E$12*Hypotheses!$E$15)*(1-Hypotheses!$E$16/2)+Hypotheses!$E$20*B$14*(1-Hypotheses!$E$28/2))*(1-(Hypotheses!$E$38+Hypotheses!$E$39))-(Hypotheses!$E$37+Hypotheses!$E$32*Hypotheses!$E$33*Hypotheses!$E$34)-(Hypotheses!$E$32*Hypotheses!$E$33*(1-Hypotheses!$E$34))-(Hypotheses!$E$35*Hypotheses!$E$36) -> 1851917.4 | C18: =(ROUND(Hypotheses!$E$6*Hypotheses!$E$7*$A18,0)*(Hypotheses!$E$10*Hypotheses!$E$13+Hypotheses!$E$11*Hypotheses!$E$14+Hypotheses!$E$12*Hypotheses!$E$15)*(1-Hypotheses!$E$16/2)+Hypotheses!$E$20*C$14*(1-Hypotheses!$E$28/2))*(1-(Hypotheses!$E$38+Hypotheses!$E$39))-(Hypotheses!$E$37+Hypotheses!$E$32*Hypotheses!$E$33*Hypotheses!$E$34)-(Hypotheses!$E$32*Hypotheses!$E$33*(1-Hypotheses!$E$34))-(Hypotheses!$E$35*Hypotheses!$E$36) -> 2145197.4 | D18: =(ROUND(Hypotheses!$E$6*Hypotheses!$E$7*$A18,0)*(Hypotheses!$E$10*Hypotheses!$E$13+Hypotheses!$E$11*Hypotheses!$E$14+Hypotheses!$E$12*Hypotheses!$E$15)*(1-Hypotheses!$E$16/2)+Hypotheses!$E$20*D$14*(1-Hypotheses!$E$28/2))*(1-(Hypotheses!$E$38+Hypotheses!$E$39))-(Hypotheses!$E$37+Hypotheses!$E$32*Hypotheses!$E$33*Hypotheses!$E$34)-(Hypotheses!$E$32*Hypotheses!$E$33*(1-Hypotheses!$E$34))-(Hypotheses!$E$35*Hypotheses!$E$36) -> 2438477.4 | E18: =(ROUND(Hypotheses!$E$6*Hypotheses!$E$7*$A18,0)*(Hypotheses!$E$10*Hypotheses!$E$13+Hypotheses!$E$11*Hypotheses!$E$14+Hypotheses!$E$12*Hypotheses!$E$15)*(1-Hypotheses!$E$16/2)+Hypotheses!$E$20*E$14*(1-Hypotheses!$E$28/2))*(1-(Hypotheses!$E$38+Hypotheses!$E$39))-(Hypotheses!$E$37+Hypotheses!$E$32*Hypotheses!$E$33*Hypotheses!$E$34)-(Hypotheses!$E$32*Hypotheses!$E$33*(1-Hypotheses!$E$34))-(Hypotheses!$E$35*Hypotheses!$E$36) -> 2927277.4 | F18: =(ROUND(Hypotheses!$E$6*Hypotheses!$E$7*$A18,0)*(Hypotheses!$E$10*Hypotheses!$E$13+Hypotheses!$E$11*Hypotheses!$E$14+Hypotheses!$E$12*Hypotheses!$E$15)*(1-Hypotheses!$E$16/2)+Hypotheses!$E$20*F$14*(1-Hypotheses!$E$28/2))*(1-(Hypotheses!$E$38+Hypotheses!$E$39))-(Hypotheses!$E$37+Hypotheses!$E$32*Hypotheses!$E$33*Hypotheses!$E$34)-(Hypotheses!$E$32*Hypotheses!$E$33*(1-Hypotheses!$E$34))-(Hypotheses!$E$35*Hypotheses!$E$36) -> 3318317.4 | G18: =(ROUND(Hypotheses!$E$6*Hypotheses!$E$7*$A18,0)*(Hypotheses!$E$10*Hypotheses!$E$13+Hypotheses!$E$11*Hypotheses!$E$14+Hypotheses!$E$12*Hypotheses!$E$15)*(1-Hypotheses!$E$16/2)+Hypotheses!$E$20*G$14*(1-Hypotheses!$E$28/2))*(1-(Hypotheses!$E$38+Hypotheses!$E$39))-(Hypotheses!$E$37+Hypotheses!$E$32*Hypotheses!$E$33*Hypotheses!$E$34)-(Hypotheses!$E$32*Hypotheses!$E$33*(1-Hypotheses!$E$34))-(Hypotheses!$E$35*Hypotheses!$E$36) -> 3807117.4 | H18: =(ROUND(Hypotheses!$E$6*Hypotheses!$E$7*$A18,0)*(Hypotheses!$E$10*Hypotheses!$E$13+Hypotheses!$E$11*Hypotheses!$E$14+Hypotheses!$E$12*Hypotheses!$E$15)*(1-Hypotheses!$E$16/2)+Hypotheses!$E$20*H$14*(1-Hypotheses!$E$28/2))*(1-(Hypotheses!$E$38+Hypotheses!$E$39))-(Hypotheses!$E$37+Hypotheses!$E$32*Hypotheses!$E$33*Hypotheses!$E$34)-(Hypotheses!$E$32*Hypotheses!$E$33*(1-Hypotheses!$E$34))-(Hypotheses!$E$35*Hypotheses!$E$36) -> 4295917.4
A19: 0.12 | B19: =(ROUND(Hypotheses!$E$6*Hypotheses!$E$7*$A19,0)*(Hypotheses!$E$10*Hypotheses!$E$13+Hypotheses!$E$11*Hypotheses!$E$14+Hypotheses!$E$12*Hypotheses!$E$15)*(1-Hypotheses!$E$16/2)+Hypotheses!$E$20*B$14*(1-Hypotheses!$E$28/2))*(1-(Hypotheses!$E$38+Hypotheses!$E$39))-(Hypotheses!$E$37+Hypotheses!$E$32*Hypotheses!$E$33*Hypotheses!$E$34)-(Hypotheses!$E$32*Hypotheses!$E$33*(1-Hypotheses!$E$34))-(Hypotheses!$E$35*Hypotheses!$E$36) -> 2141961.6 | C19: =(ROUND(Hypotheses!$E$6*Hypotheses!$E$7*$A19,0)*(Hypotheses!$E$10*Hypotheses!$E$13+Hypotheses!$E$11*Hypotheses!$E$14+Hypotheses!$E$12*Hypotheses!$E$15)*(1-Hypotheses!$E$16/2)+Hypotheses!$E$20*C$14*(1-Hypotheses!$E$28/2))*(1-(Hypotheses!$E$38+Hypotheses!$E$39))-(Hypotheses!$E$37+Hypotheses!$E$32*Hypotheses!$E$33*Hypotheses!$E$34)-(Hypotheses!$E$32*Hypotheses!$E$33*(1-Hypotheses!$E$34))-(Hypotheses!$E$35*Hypotheses!$E$36) -> 2435241.6 | D19: =(ROUND(Hypotheses!$E$6*Hypotheses!$E$7*$A19,0)*(Hypotheses!$E$10*Hypotheses!$E$13+Hypotheses!$E$11*Hypotheses!$E$14+Hypotheses!$E$12*Hypotheses!$E$15)*(1-Hypotheses!$E$16/2)+Hypotheses!$E$20*D$14*(1-Hypotheses!$E$28/2))*(1-(Hypotheses!$E$38+Hypotheses!$E$39))-(Hypotheses!$E$37+Hypotheses!$E$32*Hypotheses!$E$33*Hypotheses!$E$34)-(Hypotheses!$E$32*Hypotheses!$E$33*(1-Hypotheses!$E$34))-(Hypotheses!$E$35*Hypotheses!$E$36) -> 2728521.6 | E19: =(ROUND(Hypotheses!$E$6*Hypotheses!$E$7*$A19,0)*(Hypotheses!$E$10*Hypotheses!$E$13+Hypotheses!$E$11*Hypotheses!$E$14+Hypotheses!$E$12*Hypotheses!$E$15)*(1-Hypotheses!$E$16/2)+Hypotheses!$E$20*E$14*(1-Hypotheses!$E$28/2))*(1-(Hypotheses!$E$38+Hypotheses!$E$39))-(Hypotheses!$E$37+Hypotheses!$E$32*Hypotheses!$E$33*Hypotheses!$E$34)-(Hypotheses!$E$32*Hypotheses!$E$33*(1-Hypotheses!$E$34))-(Hypotheses!$E$35*Hypotheses!$E$36) -> 3217321.6 | F19: =(ROUND(Hypotheses!$E$6*Hypotheses!$E$7*$A19,0)*(Hypotheses!$E$10*Hypotheses!$E$13+Hypotheses!$E$11*Hypotheses!$E$14+Hypotheses!$E$12*Hypotheses!$E$15)*(1-Hypotheses!$E$16/2)+Hypotheses!$E$20*F$14*(1-Hypotheses!$E$28/2))*(1-(Hypotheses!$E$38+Hypotheses!$E$39))-(Hypotheses!$E$37+Hypotheses!$E$32*Hypotheses!$E$33*Hypotheses!$E$34)-(Hypotheses!$E$32*Hypotheses!$E$33*(1-Hypotheses!$E$34))-(Hypotheses!$E$35*Hypotheses!$E$36) -> 3608361.6 | G19: =(ROUND(Hypotheses!$E$6*Hypotheses!$E$7*$A19,0)*(Hypotheses!$E$10*Hypotheses!$E$13+Hypotheses!$E$11*Hypotheses!$E$14+Hypotheses!$E$12*Hypotheses!$E$15)*(1-Hypotheses!$E$16/2)+Hypotheses!$E$20*G$14*(1-Hypotheses!$E$28/2))*(1-(Hypotheses!$E$38+Hypotheses!$E$39))-(Hypotheses!$E$37+Hypotheses!$E$32*Hypotheses!$E$33*Hypotheses!$E$34)-(Hypotheses!$E$32*Hypotheses!$E$33*(1-Hypotheses!$E$34))-(Hypotheses!$E$35*Hypotheses!$E$36) -> 4097161.6 | H19: =(ROUND(Hypotheses!$E$6*Hypotheses!$E$7*$A19,0)*(Hypotheses!$E$10*Hypotheses!$E$13+Hypotheses!$E$11*Hypotheses!$E$14+Hypotheses!$E$12*Hypotheses!$E$15)*(1-Hypotheses!$E$16/2)+Hypotheses!$E$20*H$14*(1-Hypotheses!$E$28/2))*(1-(Hypotheses!$E$38+Hypotheses!$E$39))-(Hypotheses!$E$37+Hypotheses!$E$32*Hypotheses!$E$33*Hypotheses!$E$34)-(Hypotheses!$E$32*Hypotheses!$E$33*(1-Hypotheses!$E$34))-(Hypotheses!$E$35*Hypotheses!$E$36) -> 4585961.6
A20: 0.14 | B20: =(ROUND(Hypotheses!$E$6*Hypotheses!$E$7*$A20,0)*(Hypotheses!$E$10*Hypotheses!$E$13+Hypotheses!$E$11*Hypotheses!$E$14+Hypotheses!$E$12*Hypotheses!$E$15)*(1-Hypotheses!$E$16/2)+Hypotheses!$E$20*B$14*(1-Hypotheses!$E$28/2))*(1-(Hypotheses!$E$38+Hypotheses!$E$39))-(Hypotheses!$E$37+Hypotheses!$E$32*Hypotheses!$E$33*Hypotheses!$E$34)-(Hypotheses!$E$32*Hypotheses!$E$33*(1-Hypotheses!$E$34))-(Hypotheses!$E$35*Hypotheses!$E$36) -> 2432005.9 | C20: =(ROUND(Hypotheses!$E$6*Hypotheses!$E$7*$A20,0)*(Hypotheses!$E$10*Hypotheses!$E$13+Hypotheses!$E$11*Hypotheses!$E$14+Hypotheses!$E$12*Hypotheses!$E$15)*(1-Hypotheses!$E$16/2)+Hypotheses!$E$20*C$14*(1-Hypotheses!$E$28/2))*(1-(Hypotheses!$E$38+Hypotheses!$E$39))-(Hypotheses!$E$37+Hypotheses!$E$32*Hypotheses!$E$33*Hypotheses!$E$34)-(Hypotheses!$E$32*Hypotheses!$E$33*(1-Hypotheses!$E$34))-(Hypotheses!$E$35*Hypotheses!$E$36) -> 2725285.9 | D20: =(ROUND(Hypotheses!$E$6*Hypotheses!$E$7*$A20,0)*(Hypotheses!$E$10*Hypotheses!$E$13+Hypotheses!$E$11*Hypotheses!$E$14+Hypotheses!$E$12*Hypotheses!$E$15)*(1-Hypotheses!$E$16/2)+Hypotheses!$E$20*D$14*(1-Hypotheses!$E$28/2))*(1-(Hypotheses!$E$38+Hypotheses!$E$39))-(Hypotheses!$E$37+Hypotheses!$E$32*Hypotheses!$E$33*Hypotheses!$E$34)-(Hypotheses!$E$32*Hypotheses!$E$33*(1-Hypotheses!$E$34))-(Hypotheses!$E$35*Hypotheses!$E$36) -> 3018565.9 | E20: =(ROUND(Hypotheses!$E$6*Hypotheses!$E$7*$A20,0)*(Hypotheses!$E$10*Hypotheses!$E$13+Hypotheses!$E$11*Hypotheses!$E$14+Hypotheses!$E$12*Hypotheses!$E$15)*(1-Hypotheses!$E$16/2)+Hypotheses!$E$20*E$14*(1-Hypotheses!$E$28/2))*(1-(Hypotheses!$E$38+Hypotheses!$E$39))-(Hypotheses!$E$37+Hypotheses!$E$32*Hypotheses!$E$33*Hypotheses!$E$34)-(Hypotheses!$E$32*Hypotheses!$E$33*(1-Hypotheses!$E$34))-(Hypotheses!$E$35*Hypotheses!$E$36) -> 3507365.9 | F20: =(ROUND(Hypotheses!$E$6*Hypotheses!$E$7*$A20,0)*(Hypotheses!$E$10*Hypotheses!$E$13+Hypotheses!$E$11*Hypotheses!$E$14+Hypotheses!$E$12*Hypotheses!$E$15)*(1-Hypotheses!$E$16/2)+Hypotheses!$E$20*F$14*(1-Hypotheses!$E$28/2))*(1-(Hypotheses!$E$38+Hypotheses!$E$39))-(Hypotheses!$E$37+Hypotheses!$E$32*Hypotheses!$E$33*Hypotheses!$E$34)-(Hypotheses!$E$32*Hypotheses!$E$33*(1-Hypotheses!$E$34))-(Hypotheses!$E$35*Hypotheses!$E$36) -> 3898405.9 | G20: =(ROUND(Hypotheses!$E$6*Hypotheses!$E$7*$A20,0)*(Hypotheses!$E$10*Hypotheses!$E$13+Hypotheses!$E$11*Hypotheses!$E$14+Hypotheses!$E$12*Hypotheses!$E$15)*(1-Hypotheses!$E$16/2)+Hypotheses!$E$20*G$14*(1-Hypotheses!$E$28/2))*(1-(Hypotheses!$E$38+Hypotheses!$E$39))-(Hypotheses!$E$37+Hypotheses!$E$32*Hypotheses!$E$33*Hypotheses!$E$34)-(Hypotheses!$E$32*Hypotheses!$E$33*(1-Hypotheses!$E$34))-(Hypotheses!$E$35*Hypotheses!$E$36) -> 4387205.9 | H20: =(ROUND(Hypotheses!$E$6*Hypotheses!$E$7*$A20,0)*(Hypotheses!$E$10*Hypotheses!$E$13+Hypotheses!$E$11*Hypotheses!$E$14+Hypotheses!$E$12*Hypotheses!$E$15)*(1-Hypotheses!$E$16/2)+Hypotheses!$E$20*H$14*(1-Hypotheses!$E$28/2))*(1-(Hypotheses!$E$38+Hypotheses!$E$39))-(Hypotheses!$E$37+Hypotheses!$E$32*Hypotheses!$E$33*Hypotheses!$E$34)-(Hypotheses!$E$32*Hypotheses!$E$33*(1-Hypotheses!$E$34))-(Hypotheses!$E$35*Hypotheses!$E$36) -> 4876005.9
A21: 0.16 | B21: =(ROUND(Hypotheses!$E$6*Hypotheses!$E$7*$A21,0)*(Hypotheses!$E$10*Hypotheses!$E$13+Hypotheses!$E$11*Hypotheses!$E$14+Hypotheses!$E$12*Hypotheses!$E$15)*(1-Hypotheses!$E$16/2)+Hypotheses!$E$20*B$14*(1-Hypotheses!$E$28/2))*(1-(Hypotheses!$E$38+Hypotheses!$E$39))-(Hypotheses!$E$37+Hypotheses!$E$32*Hypotheses!$E$33*Hypotheses!$E$34)-(Hypotheses!$E$32*Hypotheses!$E$33*(1-Hypotheses!$E$34))-(Hypotheses!$E$35*Hypotheses!$E$36) -> 2722050.2 | C21: =(ROUND(Hypotheses!$E$6*Hypotheses!$E$7*$A21,0)*(Hypotheses!$E$10*Hypotheses!$E$13+Hypotheses!$E$11*Hypotheses!$E$14+Hypotheses!$E$12*Hypotheses!$E$15)*(1-Hypotheses!$E$16/2)+Hypotheses!$E$20*C$14*(1-Hypotheses!$E$28/2))*(1-(Hypotheses!$E$38+Hypotheses!$E$39))-(Hypotheses!$E$37+Hypotheses!$E$32*Hypotheses!$E$33*Hypotheses!$E$34)-(Hypotheses!$E$32*Hypotheses!$E$33*(1-Hypotheses!$E$34))-(Hypotheses!$E$35*Hypotheses!$E$36) -> 3015330.2 | D21: =(ROUND(Hypotheses!$E$6*Hypotheses!$E$7*$A21,0)*(Hypotheses!$E$10*Hypotheses!$E$13+Hypotheses!$E$11*Hypotheses!$E$14+Hypotheses!$E$12*Hypotheses!$E$15)*(1-Hypotheses!$E$16/2)+Hypotheses!$E$20*D$14*(1-Hypotheses!$E$28/2))*(1-(Hypotheses!$E$38+Hypotheses!$E$39))-(Hypotheses!$E$37+Hypotheses!$E$32*Hypotheses!$E$33*Hypotheses!$E$34)-(Hypotheses!$E$32*Hypotheses!$E$33*(1-Hypotheses!$E$34))-(Hypotheses!$E$35*Hypotheses!$E$36) -> 3308610.2 | E21: =(ROUND(Hypotheses!$E$6*Hypotheses!$E$7*$A21,0)*(Hypotheses!$E$10*Hypotheses!$E$13+Hypotheses!$E$11*Hypotheses!$E$14+Hypotheses!$E$12*Hypotheses!$E$15)*(1-Hypotheses!$E$16/2)+Hypotheses!$E$20*E$14*(1-Hypotheses!$E$28/2))*(1-(Hypotheses!$E$38+Hypotheses!$E$39))-(Hypotheses!$E$37+Hypotheses!$E$32*Hypotheses!$E$33*Hypotheses!$E$34)-(Hypotheses!$E$32*Hypotheses!$E$33*(1-Hypotheses!$E$34))-(Hypotheses!$E$35*Hypotheses!$E$36) -> 3797410.2 | F21: =(ROUND(Hypotheses!$E$6*Hypotheses!$E$7*$A21,0)*(Hypotheses!$E$10*Hypotheses!$E$13+Hypotheses!$E$11*Hypotheses!$E$14+Hypotheses!$E$12*Hypotheses!$E$15)*(1-Hypotheses!$E$16/2)+Hypotheses!$E$20*F$14*(1-Hypotheses!$E$28/2))*(1-(Hypotheses!$E$38+Hypotheses!$E$39))-(Hypotheses!$E$37+Hypotheses!$E$32*Hypotheses!$E$33*Hypotheses!$E$34)-(Hypotheses!$E$32*Hypotheses!$E$33*(1-Hypotheses!$E$34))-(Hypotheses!$E$35*Hypotheses!$E$36) -> 4188450.2 | G21: =(ROUND(Hypotheses!$E$6*Hypotheses!$E$7*$A21,0)*(Hypotheses!$E$10*Hypotheses!$E$13+Hypotheses!$E$11*Hypotheses!$E$14+Hypotheses!$E$12*Hypotheses!$E$15)*(1-Hypotheses!$E$16/2)+Hypotheses!$E$20*G$14*(1-Hypotheses!$E$28/2))*(1-(Hypotheses!$E$38+Hypotheses!$E$39))-(Hypotheses!$E$37+Hypotheses!$E$32*Hypotheses!$E$33*Hypotheses!$E$34)-(Hypotheses!$E$32*Hypotheses!$E$33*(1-Hypotheses!$E$34))-(Hypotheses!$E$35*Hypotheses!$E$36) -> 4677250.2 | H21: =(ROUND(Hypotheses!$E$6*Hypotheses!$E$7*$A21,0)*(Hypotheses!$E$10*Hypotheses!$E$13+Hypotheses!$E$11*Hypotheses!$E$14+Hypotheses!$E$12*Hypotheses!$E$15)*(1-Hypotheses!$E$16/2)+Hypotheses!$E$20*H$14*(1-Hypotheses!$E$28/2))*(1-(Hypotheses!$E$38+Hypotheses!$E$39))-(Hypotheses!$E$37+Hypotheses!$E$32*Hypotheses!$E$33*Hypotheses!$E$34)-(Hypotheses!$E$32*Hypotheses!$E$33*(1-Hypotheses!$E$34))-(Hypotheses!$E$35*Hypotheses!$E$36) -> 5166050.2
A23: LECTURE : La variable la plus sensible est le spend moyen Produit 2 (leads). Une variation +30% (15k→20k €/client) génère +100 k€ de revenu en An 1. Sur P1, passer de 5% à 8% de conversion multiplie le revenu par 1,6×. Tableau 2 : l'EBITDA An 3 reste positif sur l'ensemble de la grille testée — seuil de rentabilité atteint dès Conv 6% / Spend 15k. Priorité commerciale : valider 5 clients Baromètre + 5 clients Leads avant Q3 2026.

Sheet Build_vs_Partner
A1: Build vs Partner — Framework décisionnel pour le Lead Scoring
A2: Question : L'Étudiant doit-il développer le scoring en interne ou s'appuyer sur un fournisseur d'enrichissement ?
A4: Poste de coût | B4: BUILD (in-house) | C4: PARTNER (Bombora/ZoomInfo) | D4: HYBRIDE (Build + Partner enrichissement C) | E4: Note
A5: Setup initial (Y1) | B5: 50000 | C5: 15000 | D5: 60000 | E5: Build : intégration scoring v2 ; Partner : DPA + API
A6: Coût récurrent An 1 | B6: 240000 | C6: Variable | D6: 240000 | E6: Build : 3 ETP data × 80k ; Partner : volume trop faible
A7: Coût récurrent An 2 | B7: 332800 | C7: 60000 | D7: 392800 | E7: Partner : 200k contacts × 0,30€ moyen
A8: Coût récurrent An 3 | B8: 432640 | C8: 150000 | D8: 582640 | E8: Partner : 500k contacts × 0,30€
A9: Coût total cumulé 3 ans | B9: =SUM(B5:B8) -> 1055440 | C9: =SUM(C5:C8) -> 225000 | D9: =SUM(D5:D8) -> 1275440 | E9: SUM des lignes ci-dessus
A11: Critère | B11: Poids | C11: BUILD (1-5) | D11: PARTNER (1-5) | E11: HYBRIDE (1-5) | F11: Justification
A12: Avantage concurrentiel | B12: 0.2 | C12: 5 | D12: 1 | E12: 4 | F12: Build : signaux propriétaires (agent IA, salons)
A13: Time-to-market | B13: 0.1 | C13: 2 | D13: 5 | E13: 3 | F13: Partner : déploiement 4 semaines vs 3-4 mois Build
A14: Coût total 3 ans | B14: 0.2 | C14: 4 | D14: 5 | E14: 3 | F14: Partner moins cher si volumes faibles
A15: Conformité RGPD | B15: 0.2 | C15: 5 | D15: 2 | E15: 3 | F15: Build : contrôle total ; Partner : DPA complexe
A16: Couverture signaux | B16: 0.15 | C16: 3 | D16: 4 | E16: 5 | F16: Partner enrichit les signaux off-platform
A17: Scalabilité | B17: 0.15 | C17: 4 | D17: 4 | E17: 5 | F17: Hybride : meilleure résilience si pic de volume
A18: SCORE PONDÉRÉ | C18: =SUMPRODUCT($B$12:$B$17,C12:C17) -> 4.05 | D18: =SUMPRODUCT($B$12:$B$17,D12:D17) -> 3.3 | E18: =SUMPRODUCT($B$12:$B$17,E12:E17) -> 3.8
A20: RECOMMANDATION
A21: BUILD prioritaire sur les 3 dimensions du scoring — données propriétaires L'Étudiant. Le score pondéré favorise BUILD (avantage concurrentiel + RGPD). PARTNER d'enrichissement (Bombora/ZoomInfo) déclenché en An 2 uniquement si volume A < 60% objectif ou si écoles demandent des signaux off-platform. HYBRIDE = option de repli An 2-3.
